Metadata-Version: 2.1
Name: pytick
Version: 1.0.7
Summary: A lightweight Python library that provides a simple timer
Home-page: https://github.com/maltarouti/pytick
Author: Murtada Altarouti
Author-email: murtada.altarouti@gmail.com
License: MIT
Platform: UNKNOWN
License-File: LICENSE
